llamacloud_mcp/__init__.py
llamacloud_mcp/main.py
llama_mcp_server-0.2.0.dist-info/METADATA
llama_mcp_server-0.2.0.dist-info/WHEEL
llama_mcp_server-0.2.0.dist-info/entry_points.txt
llama_mcp_server-0.2.0.dist-info/RECORD
