Metadata-Version: 2.4
Name: llama-mcp-server
Version: 0.2.0
Summary: MCP server for document parsing with LlamaCloud multimodal understanding
Project-URL: Homepage, https://github.com/oloruntoba-madamori/llamacloud-mcp
Project-URL: Repository, https://github.com/oloruntoba-madamori/llamacloud-mcp
Author-email: Oloruntoba Madamori <oloruntoba.madamori@totogi.com>
License-Expression: MIT
Keywords: ai,document-parsing,llama,llamacloud,mcp
Classifier: Development Status :: 4 - Beta
Classifier: Intended Audience :: Developers
Classifier: License :: OSI Approved :: MIT License
Classifier: Programming Language :: Python :: 3
Classifier: Programming Language :: Python :: 3.10
Classifier: Programming Language :: Python :: 3.11
Classifier: Programming Language :: Python :: 3.12
Requires-Python: >=3.10
Requires-Dist: click
Requires-Dist: llama-cloud-services
Requires-Dist: llama-index-indices-managed-llama-cloud>=0.6.9
Requires-Dist: mcp[cli]>=1.6.0
Requires-Dist: python-dotenv>=1.1.0
